MarketVision/MarketVision.py
MarketVision/__init__.py
MarketVision-0.0.6.dist-info/LICENSE
MarketVision-0.0.6.dist-info/METADATA
MarketVision-0.0.6.dist-info/WHEEL
MarketVision-0.0.6.dist-info/top_level.txt
MarketVision-0.0.6.dist-info/RECORD
