Metadata-Version: 2.1
Name: MarketVision
Version: 0.0.6
Home-page: https://github.com/m21248074/MarketVision
Author: Kai-Wei Tian
Author-email: m.123051427@gmail.com
License-File: LICENSE
Requires-Dist: yfinance
Requires-Dist: scikit-learn
